{
  "id": "10637",
  "title": "【茨城県観光】絶景とグルメを巡るおすすめモデルコース",
  "hotel_name": "筑波山温泉　筑波山江戸屋",
  "description": "茨城県の静寂と自然に包まれる極上の大人旅へようこそ。山・海・温泉を巡り、心も体もリラックスする非日常体験が待っています。",
  "review": "<h2>茨城県の旅の魅力（テーマ: 非日常を味わう極上の大人旅）</h2>  \n<p>足を踏み入れると、尾鷲山の霞や霞ヶ浦の月光が織りなす風景が広がります。歴史ある筑波山を登れば、山頂の御神徳寺からの眺めは息を飲むほどです。食欲をそそるといえば、常陸の土産として有名な鹿沼んまいの塩と、茨城産のふぐ刺身は絶品。加えて、古都水戸の偕楽園で春の桜を眺めると、江戸時代の風情を身近に感じられます。</p>  \n\n<h2>茨城県旅行を最大限に楽しむための3つのポイント</h2>  \n<ul>  \n<li>余裕を持った日程設定。山岳・温泉・海・歴史巡りを同時に楽しみたいなら、最低4〜5日を確保。</li>  \n<li>季節ごとのイベントをチェック。秋の夕タケの石垣や、冬の埼玉銀坂松原マリオネットフェスなど、日心影響を活かした企画が豊富です。</li>  \n<li>土産店並びに地元食材を味わう。特に、筑波産のジャガイモを使ったお菓子や、江戸時代の名所をイメージしたローストビーフは必食です。</li>  \n</ul>  \n\n<h2>厳選宿泊施設のご紹介</h2>  \n\n<h3>筑波山温泉　筑波山江戸屋</h3>  \n<p>筑波山の麓に位置し、神社から徒歩数分。歴史を感じさせる櫓や庭園が古風さを演出。源泉かけ流しの温泉は身体の疲れをほぐし、対面式の日本茶体験もおすすめです。</p>  \n\n<h3>小砂温泉　ホテル美玉の湯</h3>  \n<p>小砂温泉の中心にあるホテル美玉の湯は、地下1200メートルから湧き出る天然ラドン水が自慢。24時間温熱管理された湯槽は日中でも心地よく、薬湯としても知られています。露天風呂からは四季折々の山あいが望めます。</p>  \n\n<h3>塩原温泉　明賀屋（みょうがや）本館</h3>  \n<p>江戸時代から続く歴史と自然の両立を旨とした宿。川岸に設けられた露天風呂は星空を眺めながらの入浴で、日常を離れた静寂を味わえます。また、貸切風呂で家族や仲間とゆったりとした時間を過ごすことも可能です。</p>  \n\n<p>茨城の山と海、温泉と歴史が織りなす「非日常」へ、さあ足を踏み出しませんか。大人の贅沢な時間が、あなたを待っています。\n<hr style='margin: 40px 0; border-top: 2px dashed #134e4a; opacity: 0.2;' />\n<h3 style='color: #134e4a; font-weight: bold;'>🌟 ご紹介したおすすめ厳選宿の空室・詳細はこちら</h3>\n<ul style='list-style-type: none; padding: 0;'>\n<li style='margin-bottom: 15px;'><a href='https://hb.afl.rakuten.co.jp/hgc/54d2a438.4bc4abc2.54d2a439.aa1be583/?pc=https%3A%2F%2Fimg.travel.rakuten.co.jp%2Fimage%2Ftr%2Fapi%2Fkw%2FJBe8h%2F%3Ff_no%3D10637' target='_blank' style='display: inline-block; padding: 12px 20px; background: linear-gradient(to right, #d97706, #b45309); color: white; text-decoration: none; font-weight: bold; border-radius: 12px; box-shadow: 0 4px 6px rgba(0,0,0,0.1); width: 100%; text-align: center;'>✈️ 筑波山温泉　筑波山江戸屋 の詳細プランを見る</a></li>\n<li style='margin-bottom: 15px;'><a href='https://hb.afl.rakuten.co.jp/hgc/54d2a438.4bc4abc2.54d2a439.aa1be583/?pc=https%3A%2F%2Fimg.travel.rakuten.co.jp%2Fimage%2Ftr%2Fapi%2Fkw%2FJBe8h%2F%3Ff_no%3D29385' target='_blank' style='display: inline-block; padding: 12px 20px; background: linear-gradient(to right, #d97706, #b45309); color: white; text-decoration: none; font-weight: bold; border-radius: 12px; box-shadow: 0 4px 6px rgba(0,0,0,0.1); width: 100%; text-align: center;'>✈️ 小砂温泉　ホテル美玉の湯 の詳細プランを見る</a></li>\n<li style='margin-bottom: 15px;'><a href='https://hb.afl.rakuten.co.jp/hgc/54d2a438.4bc4abc2.54d2a439.aa1be583/?pc=https%3A%2F%2Fimg.travel.rakuten.co.jp%2Fimage%2Ftr%2Fapi%2Fkw%2FJBe8h%2F%3Ff_no%3D20095' target='_blank' style='display: inline-block; padding: 12px 20px; background: linear-gradient(to right, #d97706, #b45309); color: white; text-decoration: none; font-weight: bold; border-radius: 12px; box-shadow: 0 4px 6px rgba(0,0,0,0.1); width: 100%; text-align: center;'>✈️ 塩原温泉　明賀屋（みょうがや）本館 の詳細プランを見る</a></li>\n</ul>\n",
  "image": "https://img.travel.rakuten.co.jp/share/HOTEL/10637/10637.jpg",
  "other_images": [
    "https://img.travel.rakuten.co.jp/share/HOTEL/10637/10637_ryo.jpg"
  ],
  "affiliate_url": "https://hb.afl.rakuten.co.jp/hgc/54d2a438.4bc4abc2.54d2a439.aa1be583/?pc=https%3A%2F%2Fimg.travel.rakuten.co.jp%2Fimage%2Ftr%2Fapi%2Fkw%2FJBe8h%2F%3Ff_no%3D10637",
  "prefecture": "茨城県",
  "area": "関東",
  "categories": [
    "温泉旅行"
  ],
  "price": null,
  "rating": 4.13,
  "date": "2026-07-14 05:26:34"
}