{
  "id": "76869",
  "title": "【徳島観光】阿波の風情を感じる名所めぐり＆徳島市内のおすすめホテル",
  "hotel_name": "ホテルたいよう農園　徳島県庁前",
  "description": "吉野川や鳴門の渦潮など、豊かな自然が魅力の徳島県観光特集。阿波おどりの歴史に触れる体験や、ご当地名物の周辺ランチを巡るモデルコースをご紹介。旅の拠点として便利でアメニティも充実した人気のホテルをまとめてお届けします。",
  "review": "<h2>阿波の風情と大自然。徳島県で楽しむ絶景と美食を巡る旅</h2>\n<p>吉野川の清流や鳴門海峡の荒波など、ダイナミックな自然に彩られた徳島県。ここは、歴史ある「阿波おどり」の熱気を感じる文化と、山海の恵みが詰まった「徳島ラーメン」や「阿波尾鶏」などのご当地グルメが共存する魅力あふれるエリアです。今回は、徳島観光を快適に楽しむためのモデルコースと、旅の拠点として便利なおすすめホテルをご紹介します。</p>\n\n<h3>徳島旅行を最大限に楽しむための3つのポイント</h3>\n<ul>\n  <li><strong>迫力満点！「鳴門の渦潮」を体感：</strong>観潮船に乗って間近で渦潮を見るのもよし、大鳴門橋の遊歩道「渦の道」からガラス越しに真上から見下ろす絶景もおすすめです。</li>\n  <li><strong>街中で味わう美味しい周辺ランチと地魚：</strong>徳島駅周辺や県庁前エリアでは、甘辛く煮た豚肉が特徴の「徳島ラーメン」や、新鮮な鳴門鯛のお刺身などを周辺ランチで気軽に楽しめます。</li>\n  <li><strong>徳島市街を拠点にしたスムーズなアクセス：</strong>市中心部に宿を構えることで、東の鳴門エリアや南のひょうたん島クルーズ、西の祖谷渓（いやけい）といった人気スポットへの観光ルートが綺麗に繋がります。</li>\n</ul>\n\n<h3>1. 徳島観光の魅力と知る人ぞ知る穴場散策</h3>\n<p>徳島市内の中心部には、吉野川の支流に囲まれた「ひょうたん島」と呼ばれるエリアがあり、気軽に乗れる周遊クルーズが人気です。また、伝統芸能に触れられる「阿波おどり会館」では、一年中本場の踊りを体験できるため、初めての徳島観光には欠かせない名所です。散策の合間に地元のカフェに立ち寄り、特産の「すだち」を使った爽やかなスイーツやドリンクを味わうのも楽しい時間。眉山の山頂へ登れば、徳島市街を一望できる美しい景色が広がり、心がすっきりとリフレッシュされます。</p>\n\n<h3>2. 観光に便利で快適に過ごせるおすすめ宿3選</h3>\n<p>徳島観光やビジネスの拠点として、アクセスが良好でクチコミ評価も高いおすすめの宿泊施設を厳選してご紹介します。</p>\n\n<h4>ホテルたいよう農園　徳島県庁前</h4>\n<p>「農園直営」ならではの新鮮なこだわり野菜を使った朝食バイキングが、口コミでも美味しいと好評のホテルです。徳島県庁のすぐ近くに位置し、主要観光地へのアクセスも非常にスムーズ。必要なアメニティが揃っており、出張からカップル、ファミリーでの旅行まで、アットホームで快適な滞在をサポートしてくれます。</p>\n\n<h4>ロイヤルガーデンホテル＜徳島県＞</h4>\n<p>徳島市の繁華街近くに佇む、落ち着いた雰囲気が魅力のホテル。周辺ランチや夜のご当地グルメ巡り、地酒が美味しい居酒屋へのアクセスが徒歩圏内と非常に良好です。広々とした清潔感のある客室に必要な設備やアメニティが完備されており、のんびりとした夜を過ごすことができます。</p>\n\n<h4>ホテル千秋閣＜徳島県＞</h4>\n<p>徳島駅から歩いて行ける距離にあり、ビジネスや観光のどちらの拠点としても抜群の立地を誇るホテル。最上階にあるレストランからは眉山や市街地の美しい夜景を望むことができ、旅のディナータイムを素敵に演出してくれます。丁寧なおもてなしは、カップルの旅行にも最適です。</p>\n\n<hr style='margin: 40px 0; border-top: 2px dashed #134e4a; opacity: 0.2;' />\n<h3 style='color: #134e4a; font-weight: bold;'>🌟 ご紹介したおすすめ厳選宿の空室・詳細はこちら</h3>\n<ul style='list-style-type: none; padding: 0;'>\n<li style='margin-bottom: 15px;'><a href='https://hb.afl.rakuten.co.jp/hgc/54d2a438.4bc4abc2.54d2a439.aa1be583/?pc=https%3A%2F%2Fimg.travel.rakuten.co.jp%2Fimage%2Ftr%2Fapi%2Fkw%2FJBe8h%2F%3Ff_no%3D76869' target='_blank' style='display: inline-block; padding: 12px 20px; background: linear-gradient(to right, #d97706, #b45309); color: white; text-decoration: none; font-weight: bold; border-radius: 12px; box-shadow: 0 4px 6px rgba(0,0,0,0.1); width: 100%; text-align: center;'>✈️ ホテルたいよう農園　徳島県庁前 の詳細プランを見る</a></li>\n<li style='margin-bottom: 15px;'><a href='https://hb.afl.rakuten.co.jp/hgc/54d2a438.4bc4abc2.54d2a439.aa1be583/?pc=https%3A%2F%2Fimg.travel.rakuten.co.jp%2Fimage%2Ftr%2Fapi%2Fkw%2FJBe8h%2F%3Ff_no%3D13939' target='_blank' style='display: inline-block; padding: 12px 20px; background: linear-gradient(to right, #d97706, #b45309); color: white; text-decoration: none; font-weight: bold; border-radius: 12px; box-shadow: 0 4px 6px rgba(0,0,0,0.1); width: 100%; text-align: center;'>✈️ ロイヤルガーデンホテル＜徳島県＞ の詳細プランを見る</a></li>\n<li style='margin-bottom: 15px;'><a href='https://hb.afl.rakuten.co.jp/hgc/54d2a438.4bc4abc2.54d2a439.aa1be583/?pc=https%3A%2F%2Fimg.travel.rakuten.co.jp%2Fimage%2Ftr%2Fapi%2Fkw%2FJBe8h%2F%3Ff_no%3D28052' target='_blank' style='display: inline-block; padding: 12px 20px; background: linear-gradient(to right, #d97706, #b45309); color: white; text-decoration: none; font-weight: bold; border-radius: 12px; box-shadow: 0 4px 6px rgba(0,0,0,0.1); width: 100%; text-align: center;'>✈️ ホテル千秋閣＜徳島県＞ の詳細プランを見る</a></li>\n</ul>",
  "image": "https://img.travel.rakuten.co.jp/share/HOTEL/76869/76869.jpg",
  "other_images": [
    "https://img.travel.rakuten.co.jp/share/HOTEL/76869/76869_sin.jpg"
  ],
  "affiliate_url": "https://hb.afl.rakuten.co.jp/hgc/54d2a438.4bc4abc2.54d2a439.aa1be583/?pc=https%3A%2F%2Fimg.travel.rakuten.co.jp%2Fimage%2Ftr%2Fapi%2Fkw%2FJBe8h%2F%3Ff_no%3D76869",
  "prefecture": "徳島県",
  "area": "四国",
  "categories": [
    "ファミリー・女子旅"
  ],
  "price": null,
  "rating": 4.14,
  "date": "2026-06-28 19:13:44"
}